{"CCC": {"network": "CI", "channels": ["HHZ", "HHE", "HHN"], "coords": [35.52495, -117.36453, 670.0]}, "CA01": {"network": "GS", "channels": ["HH2", "HH1", "HHZ"], "coords": [35.66512, -117.42368, 570.4]}, "CA03": {"network": "GS", "channels": ["HH2", "HH1", "HHZ"], "coords": [35.62204, -117.56911, 762.2]}, "CA04": {"network": "GS", "channels": ["HH2", "HH1", "HHZ"], "coords": [35.47833, -117.5602, 1005.4]}, "CA05": {"network": "GS", "channels": ["HH2", "HH1", "HHZ"], "coords": [35.58926, -117.28689, 612.1]}, "CA06": {"network": "GS", "channels": ["HH2", "HH1", "HHZ"], "coords": [35.59962, -117.49268, 796.4]}, "B917": {"network": "PB", "channels": ["EHZ", "EH2", "EH1"], "coords": [35.4053, -117.2588, 1192.0]}, "B921": {"network": "PB", "channels": ["EHZ", "EH2", "EH1"], "coords": [35.5865, -117.4622, 694.5]}, "SV01": {"network": "ZY", "channels": ["HHZ", "HHE", "HHN"], "coords": [35.6455, -117.4776, 602.0]}, "SV06": {"network": "ZY", "channels": ["HHZ", "HHE", "HHN"], "coords": [35.6012, -117.3811, 597.9]}, "SV08": {"network": "ZY", "channels": ["HHZ", "HHE", "HHN"], "coords": [35.5761, -117.4187, 604.0]}, "R55": {"network": "3J", "channels": ["DPE", "DPN", "DPZ"], "coords": [35.637807, -117.375649, 509.8]}, "R56": {"network": "3J", "channels": ["DPE", "DPN", "DPZ"], "coords": [35.63715, -117.287727, 510.0]}, "R64": {"network": "3J", "channels": ["DPE", "DPN", "DPZ"], "coords": [35.544053, -117.482829, 673.6]}, "R73B": {"network": "3J", "channels": ["DPE", "DPN", "DPZ"], "coords": [35.470076, -117.590971, 1042.0]}, "R74": {"network": "3J", "channels": ["DPE", "DPN", "DPZ"], "coords": [35.464912, -117.506316, 880.4]}, "RCS10": {"network": "7Q", "channels": ["HN2", "HN1", "HNZ"], "coords": [35.4862, -117.4905, 774.0]}, "RCW21": {"network": "7Q", "channels": ["EHZ", "EH2", "EH1"], "coords": [35.5395, -117.5779, 918.0]}, "RCW22": {"network": "7Q", "channels": ["EHZ", "EH2", "EH1"], "coords": [35.557, -117.464, 678.0]}, "RCW24": {"network": "7Q", "channels": ["EHZ", "EH2", "EH1"], "coords": [35.4286, -117.5817, 1006.0]}}